[
  {
    "name": "alchemy",
    "key ability": "INT",
    "trained only": true,
    "armor check penalty": false
  },
  {
    "name": "animal empathy",
    "key ability": "CHA",
    "trained only": true,
    "armor check penalty": false
  },
  {
    "name": "appraise",
    "key ability": "INT",
    "trained only": false,
    "armor check penalty": false
  },
  {
    "name": "autohypnosis",
    "key ability": "WIS",
    "trained only": true,
    "armor check penalty": false
  },
  {
    "name": "balance",
    "key ability": "DEX",
    "trained only": false,
    "armor check penalty": true
  },
  {
    "name": "bluff",
    "key ability": "CHA",
    "trained only": false,
    "armor check penalty": false
  },
  {
    "name": "climb",
    "key ability": "STR",
    "trained only": false,
    "armor check penalty": true
  },
  {
    "name": "concentration",
    "key ability": "CON",
    "trained only": false,
    "armor check penalty": false
  },
  {
    "name": "control shape",
    "key ability": "WIS",
    "trained only": false,
    "armor check penalty": false
  },
  {
    "name": "craft",
    "key ability": "INT",
    "trained only": false,
    "armor check penalty": false
  },
  {
    "name": "decipher script",
    "key ability": "INT",
    "trained only": true,
    "armor check penalty": false
  },
  {
    "name": "diplomacy",
    "key ability": "CHA",
    "trained only": false,
    "armor check penalty": false
  },
  {
    "name": "disable device",
    "key ability": "INT",
    "trained only": true,
    "armor check penalty": false
  },
  {
    "name": "disguise",
    "key ability": "CHA",
    "trained only": false,
    "armor check penalty": false
  },
  {
    "name": "escape artist",
    "key ability": "DEX",
    "trained only": false,
    "armor check penalty": true
  },
  {
    "name": "forgery",
    "key ability": "INT",
    "trained only": false,
    "armor check penalty": false
  },
  {
    "name": "gather information",
    "key ability": "CHA",
    "trained only": false,
    "armor check penalty": false
  },
  {
    "name": "handle animal",
    "key ability": "CHA",
    "trained only": true,
    "armor check penalty": false
  },
  {
    "name": "heal",
    "key ability": "WIS",
    "trained only": false,
    "armor check penalty": false
  },
  {
    "name": "hide",
    "key ability": "DEX",
    "trained only": false,
    "armor check penalty": true
  },
  {
    "name": "iaijutsu focus",
    "key ability": "CHA",
    "trained only": false,
    "armor check penalty": false
  },
  {
    "name": "innuendo",
    "key ability": "WIS",
    "trained only": true,
    "armor check penalty": false
  },
  {
    "name": "intimidate",
    "key ability": "CHA",
    "trained only": false,
    "armor check penalty": false
  },
  {
    "name": "intuit direction",
    "key ability": "WIS",
    "trained only": true,
    "armor check penalty": false
  },
  {
    "name": "jump",
    "key ability": "STR",
    "trained only": false,
    "armor check penalty": true
  },
  {
    "name": "knowledge",
    "key ability": "INT",
    "trained only": true,
    "armor check penalty": false
  },
  {
    "name": "knowledge (arcana)",
    "key ability": "INT",
    "trained only": true,
    "armor check penalty": false
  },
  {
    "name": "knowledge (architecture and engineering)",
    "key ability": "INT",
    "trained only": true,
    "armor check penalty": false
  },
  {
    "name": "knowledge (barbarian lore)",
    "key ability": "INT",
    "trained only": true,
    "armor check penalty": false
  },
  {
    "name": "knowledge (code of martial honor)",
    "key ability": "INT",
    "trained only": false,
    "armor check penalty": false
  },
  {
    "name": "knowledge (dungeoneering)",
    "key ability": "INT",
    "trained only": true,
    "armor check penalty": false
  },
  {
    "name": "knowledge (geography)",
    "key ability": "INT",
    "trained only": true,
    "armor check penalty": false
  },
  {
    "name": "knowledge (history)",
    "key ability": "INT",
    "trained only": true,
    "armor check penalty": false
  },
  {
    "name": "knowledge (law)",
    "key ability": "INT",
    "trained only": false,
    "armor check penalty": false
  },
  {
    "name": "knowledge (local)",
    "key ability": "INT",
    "trained only": true,
    "armor check penalty": false
  },
  {
    "name": "knowledge (nature)",
    "key ability": "INT",
    "trained only": true,
    "armor check penalty": false
  },
  {
    "name": "knowledge (nobility and royalty)",
    "key ability": "INT",
    "trained only": true,
    "armor check penalty": false
  },
  {
    "name": "knowledge (psionics)",
    "key ability": "INT",
    "trained only": true,
    "armor check penalty": false
  },
  {
    "name": "knowledge (religion)",
    "key ability": "INT",
    "trained only": true,
    "armor check penalty": false
  },
  {
    "name": "knowledge (Shadowlands)",
    "key ability": "INT",
    "trained only": true,
    "armor check penalty": false
  },
  {
    "name": "knowledge (spirits)",
    "key ability": "INT",
    "trained only": true,
    "armor check penalty": false
  },
  {
    "name": "knowledge (tactics)",
    "key ability": "INT",
    "trained only": false,
    "armor check penalty": false
  },
  {
    "name": "knowledge (the planes)",
    "key ability": "INT",
    "trained only": true,
    "armor check penalty": false
  },
  {
    "name": "knowledge (War)",
    "key ability": "INT",
    "trained only": true,
    "armor check penalty": false
  },
  {
    "name": "knowledge (weaponry)",
    "key ability": "INT",
    "trained only": false,
    "armor check penalty": false
  },
  {
    "name": "listen",
    "key ability": "WIS",
    "trained only": false,
    "armor check penalty": false
  },
  {
    "name": "lucid Dreaming",
    "key ability": "WIS",
    "trained only": true,
    "armor check penalty": false
  },
  {
    "name": "martial Lore",
    "key ability": "INT",
    "trained only": true,
    "armor check penalty": false
  },
  {
    "name": "move silently",
    "key ability": "DEX",
    "trained only": false,
    "armor check penalty": true
  },
  {
    "name": "open lock",
    "key ability": "DEX",
    "trained only": true,
    "armor check penalty": false
  },
  {
    "name": "perform",
    "key ability": "CHA",
    "trained only": false,
    "armor check penalty": false
  },
  {
    "name": "pick pocket",
    "key ability": "DEX",
    "trained only": true,
    "armor check penalty": true
  },
  {
    "name": "profession",
    "key ability": "WIS",
    "trained only": true,
    "armor check penalty": false
  },
  {
    "name": "psicraft",
    "key ability": "INT",
    "trained only": true,
    "armor check penalty": false
  },
  {
    "name": "read lips",
    "key ability": "INT",
    "trained only": true,
    "armor check penalty": false
  },
  {
    "name": "ride",
    "key ability": "DEX",
    "trained only": false,
    "armor check penalty": false
  },
  {
    "name": "scry",
    "key ability": "INT",
    "trained only": true,
    "armor check penalty": false
  },
  {
    "name": "search",
    "key ability": "INT",
    "trained only": false,
    "armor check penalty": false
  },
  {
    "name": "sense motive",
    "key ability": "WIS",
    "trained only": false,
    "armor check penalty": false
  },
  {
    "name": "sleight of hand",
    "key ability": "DEX",
    "trained only": true,
    "armor check penalty": true
  },
  {
    "name": "spellcraft",
    "key ability": "INT",
    "trained only": true,
    "armor check penalty": false
  },
  {
    "name": "spot",
    "key ability": "WIS",
    "trained only": false,
    "armor check penalty": false
  },
  {
    "name": "survival",
    "key ability": "WIS",
    "trained only": false,
    "armor check penalty": false
  },
  {
    "name": "swim",
    "key ability": "STR",
    "trained only": false,
    "armor check penalty": true
  },
  {
    "name": "truespeak",
    "key ability": "INT",
    "trained only": true,
    "armor check penalty": false
  },
  {
    "name": "tumble",
    "key ability": "DEX",
    "trained only": true,
    "armor check penalty": true
  },
  {
    "name": "use magic device",
    "key ability": "CHA",
    "trained only": true,
    "armor check penalty": false
  },
  {
    "name": "use psionic device",
    "key ability": "CHA",
    "trained only": true,
    "armor check penalty": false
  },
  {
    "name": "use rope",
    "key ability": "DEX",
    "trained only": false,
    "armor check penalty": false
  },
  {
    "name": "wilderness lore",
    "key ability": "WIS",
    "trained only": false,
    "armor check penalty": false
  }
]